mo_files/__init__.py
mo_files/mimetype.py
mo_files/url.py
mo_files-6.690.25168.dist-info/licenses/LICENSE
mo_files-6.690.25168.dist-info/METADATA
mo_files-6.690.25168.dist-info/WHEEL
mo_files-6.690.25168.dist-info/top_level.txt
mo_files-6.690.25168.dist-info/RECORD
