Metadata-Version: 2.4
Name: mo-files
Version: 6.690.25168
Summary: More Files! Steamlined for UTF8 and JSON.
Home-page: https://github.com/klahnakoski/mo-files
Author: Kyle Lahnakoski
Author-email: kyle@lahnakoski.com
License: MPL 2.0
Classifier: Development Status :: 4 - Beta
Classifier: Programming Language :: Python :: 3.8
Classifier: Programming Language :: Python :: 3.9
Classifier: Topic :: Software Development :: Libraries
Classifier: Topic :: Software Development :: Libraries :: Python Modules
Classifier: License :: OSI Approved :: Mozilla Public License 2.0 (MPL 2.0)
Classifier: Programming Language :: Python :: 3.10
Classifier: Programming Language :: Python :: 3.11
Classifier: Programming Language :: Python :: 3.12
Classifier: Programming Language :: Python :: 3.13
License-File: LICENSE
Requires-Dist: mo-dots==10.685.25166
Requires-Dist: mo-future==7.685.25166
Requires-Dist: mo-json==6.686.25166
Requires-Dist: mo-logs==8.685.25166
Requires-Dist: mo-math==7.685.25166
Provides-Extra: tests
Requires-Dist: mo-testing>=8.685.25166; extra == "tests"
Dynamic: author
Dynamic: author-email
Dynamic: classifier
Dynamic: description
Dynamic: description-content-type
Dynamic: home-page
Dynamic: license
Dynamic: license-file
Dynamic: provides-extra
Dynamic: requires-dist
Dynamic: summary
